designerz/__init__.py
designerz/behavior/__init__.py
designerz/behavior/explan.py
designerz/behavior/fwz.py
designerz/behavior/mediator.py
designerz/behavior/memento.py
designerz/behavior/order.py
designerz/behavior/responsibility.py
designerz/behavior/state.py
designerz/behavior/steg.py
designerz/behavior/template.py
designerz/behavior/watcher.py
designerz/creater/__init__.py
designerz/creater/abcfactory.py
designerz/creater/builder.py
designerz/creater/factory.py
designerz/creater/origin.py
designerz/creater/single.py
designerz/struct/__init__.py
designerz/struct/adapter.py
designerz/struct/agent.py
designerz/struct/appearance.py
designerz/struct/combo.py
designerz/struct/connect.py
designerz/struct/decorator.py
designerz/struct/shareyuan.py
designerz-0.1.3.dist-info/METADATA
designerz-0.1.3.dist-info/WHEEL
designerz-0.1.3.dist-info/top_level.txt
designerz-0.1.3.dist-info/RECORD
