Metadata-Version: 2.4
Name: designerz
Version: 0.1.3
Summary: Add your description here
Requires-Python: >=3.10
Requires-Dist: toml>=0.10.2
